file3/__init__.py
file3/binarys.py
file3/chars.py
file3/hexadecimals.py
file3/integers.py
file3/strings.py
test/__init__.py
test/test_chars.py
file3-0.1.7.dist-info/LICENSE
file3-0.1.7.dist-info/METADATA
file3-0.1.7.dist-info/WHEEL
file3-0.1.7.dist-info/top_level.txt
file3-0.1.7.dist-info/RECORD
