Metadata-Version: 2.1
Name: file3
Version: 0.1.7
Summary: Converting Files and Types
Home-page: https://github.com/israeljcunha/file3
Author: Israel Cunha
Author-email: israelcunhamail@gmail.com
License: MIT License
Keywords: file files file3
Platform: Linux
Platform: Windows
Platform: MacOS
Classifier: Programming Language :: Python :: 3
Classifier: Programming Language :: Python :: 3.6
Classifier: Programming Language :: Python :: 3.7
Classifier: Programming Language :: Python :: 3.8
Classifier: Programming Language :: Python :: 3.9
Classifier: Operating System :: OS Independent
Requires-Python: >=3
License-File: LICENSE
